depyro/__init__.py
depyro/constants.py
depyro/core.py
depyro-1.0.0.dist-info/LICENSE
depyro-1.0.0.dist-info/METADATA
depyro-1.0.0.dist-info/WHEEL
depyro-1.0.0.dist-info/top_level.txt
depyro-1.0.0.dist-info/RECORD
