Metadata-Version: 2.1
Name: depyro
Version: 1.0.0
Summary: A wrapper for the De Giro API to fetch portfolio data
Home-page: https://github.com/danielsteman/depyro
Author: Daniel Steman
Author-email: daniel-steman@live.nl
License: UNKNOWN
Project-URL: Bug Tracker, https://github.com/danielsteman/depyro/issues
Platform: UNKNOWN
Classifier: Programming Language :: Python :: 3
Classifier: License :: OSI Approved :: MIT License
Classifier: Operating System :: OS Independent
Requires-Python: >=3.6
License-File: LICENSE
Requires-Dist: python-dotenv (==0.19.2)
Requires-Dist: requests (==2.26.0)
